panini/__init__.py
panini/app.py
panini/async_test_client.py
panini/emulator_client.py
panini/exceptions.py
panini/test_client.py
panini/http_server/__init__.py
panini/http_server/http_server_app.py
panini/managers/__init__.py
panini/managers/event_manager.py
panini/managers/middleware_manager.py
panini/managers/nats_client.py
panini/managers/schema_manager.py
panini/managers/task_manager.py
panini/middleware/__init__.py
panini/middleware/debug_middleware.py
panini/middleware/error.py
panini/middleware/nats_timeout.py
panini/middleware/prometheus_monitoring.py
panini/middleware/reader_emulator_middleware.py
panini/middleware/tracing_middleware.py
panini/middleware/writer_emulator_middleware.py
panini/utils/__init__.py
panini/utils/helper.py
panini/utils/logger.py
panini/utils/singleton.py
panini-0.8.4.dist-info/LICENSE.md
panini-0.8.4.dist-info/METADATA
panini-0.8.4.dist-info/WHEEL
panini-0.8.4.dist-info/top_level.txt
panini-0.8.4.dist-info/RECORD
